<?xml version="1.0" encoding="UTF-8"?><?xml-stylesheet type='text/xsl' href='_UpgradeReport_Files/UpgradeReport.xslt'?><UpgradeLog>
<Properties><Property Name="Solution" Value="MessageAutoDispose">
</Property><Property Name="解决方案文件" Value="F:\CPP\MessageAutoDispose\MessageAutoDispose\MessageAutoDispose.sln">
</Property><Property Name="用户选项文件" Value="F:\CPP\MessageAutoDispose\MessageAutoDispose\MessageAutoDispose.suo">
</Property><Property Name="Date" Value="2012年6月1日">
</Property><Property Name="Time" Value="10:06">
</Property></Properties><Event ErrorLevel="0" Project="" Source="MessageAutoDispose.sln" Description="文件已成功备份为 F:\CPP\MessageAutoDispose\MessageAutoDispose\MessageAutoDispose.sln.old">
</Event><Event ErrorLevel="0" Project="" Source="MessageAutoDispose.suo" Description="文件已成功备份为 F:\CPP\MessageAutoDispose\MessageAutoDispose\MessageAutoDispose.suo.old">
</Event><Event ErrorLevel="0" Project="MessageAutoDispose" Source="MessageAutoDispose\MessageAutoDispose.vcproj" Description="Converting project file 'F:\CPP\MessageAutoDispose\MessageAutoDispose\MessageAutoDispose\MessageAutoDispose.vcproj'.">
</Event><Event ErrorLevel="1" Project="MessageAutoDispose" Source="MessageAutoDispose\MessageAutoDispose.vcproj" Description="VCWebServiceProxyGeneratorTool is no longer supported. The tool has been removed from your project settings.">
</Event><Event ErrorLevel="0" Project="MessageAutoDispose" Source="MessageAutoDispose\MessageAutoDispose.vcproj" Description="Done converting to new project file 'F:\CPP\MessageAutoDispose\MessageAutoDispose\MessageAutoDispose\MessageAutoDispose.vcxproj'.">
</Event><Event ErrorLevel="3" Project="MessageAutoDispose" Source="MessageAutoDispose\MessageAutoDispose.vcproj" Description="Converted">
</Event><Event ErrorLevel="0" Project="" Source="MessageAutoDispose.sln" Description="成功转换解决方案">
</Event><Event ErrorLevel="3" Project="" Source="MessageAutoDispose.sln" Description="Converted">
</Event></UpgradeLog>